ifea/__init__.py
ifea-2024.3.24.dist-info/LICENSE
ifea-2024.3.24.dist-info/METADATA
ifea-2024.3.24.dist-info/WHEEL
ifea-2024.3.24.dist-info/top_level.txt
ifea-2024.3.24.dist-info/RECORD
