Metadata-Version: 2.1
Name: ifea
Version: 2024.3.24
Summary: ifea
Home-page: https://github.com/usnistgov/ifea
Author: Kamal Choudhary
Author-email: kamal.choudhary@nist.gov
Classifier: Programming Language :: Python :: 3
Classifier: License :: OSI Approved :: MIT License
Classifier: Operating System :: OS Independent
Requires-Python: >=3.9
License-File: LICENSE
Requires-Dist: numpy >=1.22.0
Requires-Dist: scipy >=1.6.3
Requires-Dist: jarvis-tools >=2021.07.19
Requires-Dist: pydantic-settings
